mocoo/__init__.py
mocoo/agent.py
mocoo/environment.py
mocoo/mixin.py
mocoo/model.py
mocoo/module.py
mocoo/utils.py
mocoo-0.0.3.dist-info/licenses/LICENSE
mocoo-0.0.3.dist-info/METADATA
mocoo-0.0.3.dist-info/WHEEL
mocoo-0.0.3.dist-info/top_level.txt
mocoo-0.0.3.dist-info/RECORD
