Metadata-Version: 2.4
Name: mocoo
Version: 0.0.3
Summary: Momentum Contrast ODE-Regularized VAE for Single-Cell RNA Velocity
Home-page: https://github.com/PeterPonyu/MoCoO
Author: Peter Ponyu
Author-email: Peter Ponyu <peter.ponyu@example.com>
Maintainer-email: Peter Ponyu <peter.ponyu@example.com>
License-Expression: MIT
Project-URL: Homepage, https://github.com/PeterPonyu/MoCoO
Project-URL: Documentation, https://mocoo.readthedocs.io/
Project-URL: Repository, https://github.com/PeterPonyu/MoCoO
Project-URL: Issues, https://github.com/PeterPonyu/MoCoO/issues
Project-URL: Changelog, https://github.com/PeterPonyu/MoCoO/blob/main/CHANGELOG.md
Project-URL: Discussions, https://github.com/PeterPonyu/MoCoO/discussions
Keywords: single-cell,RNA-seq,VAE,ODE,MoCo,trajectory,velocity
Classifier: Development Status :: 3 - Alpha
Classifier: Intended Audience :: Science/Research
Classifier: Operating System :: OS Independent
Classifier: Programming Language :: Python :: 3
Classifier: Programming Language :: Python :: 3.8
Classifier: Programming Language :: Python :: 3.9
Classifier: Programming Language :: Python :: 3.10
Classifier: Programming Language :: Python :: 3.11
Classifier: Topic :: Scientific/Engineering :: Bio-Informatics
Requires-Python: >=3.8
License-File: LICENSE
Requires-Dist: torch>=1.12.0
Requires-Dist: torchdiffeq>=0.2.3
Requires-Dist: numpy>=1.21.0
Requires-Dist: scipy>=1.7.0
Requires-Dist: scikit-learn>=1.0.0
Requires-Dist: anndata>=0.8.0
Requires-Dist: scanpy>=1.9.0
Requires-Dist: tqdm>=4.62.0
Requires-Dist: pandas>=1.3.0
Provides-Extra: dev
Requires-Dist: pytest>=7.0.0; extra == "dev"
Requires-Dist: pytest-cov>=4.0.0; extra == "dev"
Requires-Dist: black>=22.0.0; extra == "dev"
Requires-Dist: isort>=5.10.0; extra == "dev"
Requires-Dist: flake8>=4.0.0; extra == "dev"
Requires-Dist: mypy>=0.950; extra == "dev"
Requires-Dist: jupyter>=1.0.0; extra == "dev"
Requires-Dist: ipykernel>=6.0.0; extra == "dev"
Provides-Extra: docs
Requires-Dist: sphinx>=4.0.0; extra == "docs"
Requires-Dist: sphinx-rtd-theme>=1.0.0; extra == "docs"
Requires-Dist: myst-parser>=0.18.0; extra == "docs"
Dynamic: license-file
